[
    {
        "key": "group_640be5364d26a",
        "title": "Post Meta Fields",
        "fields": [
            {
                "key": "field_640be5369ab36",
                "label": "Post Title",
                "name": "post_title",
                "aria-label": "",
                "type": "text",
                "instructions": "",
                "required": 0,
                "conditional_logic": 0,
                "wrapper": {
                    "width": "",
                    "class": "",
                    "id": ""
                },
                "default_value": "",
                "maxlength": "",
                "placeholder": "",
                "prepend": "",
                "append": ""
            },
            {
                "key": "field_640be54f9ab37",
                "label": "Thumbnail Image",
                "name": "thumbnail_image",
                "aria-label": "",
                "type": "image",
                "instructions": "",
                "required": 0,
                "conditional_logic": 0,
                "wrapper": {
                    "width": "",
                    "class": "",
                    "id": ""
                },
                "return_format": "array",
                "library": "all",
                "min_width": "",
                "min_height": "",
                "min_size": "",
                "max_width": "",
                "max_height": "",
                "max_size": "",
                "mime_types": "",
                "preview_size": "medium"
            },
            {
                "key": "field_640c0f6579a55",
                "label": "Description section",
                "name": "description_section",
                "aria-label": "",
                "type": "repeater",
                "instructions": "",
                "required": 0,
                "conditional_logic": 0,
                "wrapper": {
                    "width": "",
                    "class": "",
                    "id": ""
                },
                "min": 0,
                "max": 0,
                "layout": "table",
                "button_label": "",
                "collapsed": "",
                "sub_fields": [
                    {
                        "key": "field_640c0f7979a56",
                        "label": "Type",
                        "name": "type",
                        "aria-label": "",
                        "type": "select",
                        "instructions": "",
                        "required": 0,
                        "conditional_logic": 0,
                        "wrapper": {
                            "width": "",
                            "class": "",
                            "id": ""
                        },
                        "choices": {
                            "paragraph": "Paragraph",
                            "list": "List",
                            "quote": "Quote",
                            "image": "Image"
                        },
                        "default_value": false,
                        "return_format": "value",
                        "multiple": 0,
                        "allow_null": 0,
                        "ui": 0,
                        "ajax": 0,
                        "placeholder": ""
                    },
                    {
                        "key": "field_640c0fb579a57",
                        "label": "Description",
                        "name": "description",
                        "aria-label": "",
                        "type": "textarea",
                        "instructions": "",
                        "required": 0,
                        "conditional_logic": 0,
                        "wrapper": {
                            "width": "",
                            "class": "",
                            "id": ""
                        },
                        "default_value": "",
                        "maxlength": "",
                        "rows": "",
                        "placeholder": "",
                        "new_lines": ""
                    },
                    {
                        "key": "field_640c1f2085060",
                        "label": "Description Image",
                        "name": "description_image",
                        "aria-label": "",
                        "type": "image",
                        "instructions": "",
                        "required": 0,
                        "conditional_logic": 0,
                        "wrapper": {
                            "width": "",
                            "class": "",
                            "id": ""
                        },
                        "return_format": "array",
                        "library": "all",
                        "min_width": "",
                        "min_height": "",
                        "min_size": "",
                        "max_width": "",
                        "max_height": "",
                        "max_size": "",
                        "mime_types": "",
                        "preview_size": "medium"
                    }
                ]
            },
            {
                "key": "field_640c100f52cd8",
                "label": "FAQs",
                "name": "faqs",
                "aria-label": "",
                "type": "repeater",
                "instructions": "",
                "required": 0,
                "conditional_logic": 0,
                "wrapper": {
                    "width": "",
                    "class": "",
                    "id": ""
                },
                "min": 0,
                "max": 0,
                "layout": "table",
                "button_label": "",
                "collapsed": "",
                "sub_fields": [
                    {
                        "key": "field_640c102a52cd9",
                        "label": "Question",
                        "name": "question",
                        "aria-label": "",
                        "type": "text",
                        "instructions": "",
                        "required": 0,
                        "conditional_logic": 0,
                        "wrapper": {
                            "width": "",
                            "class": "",
                            "id": ""
                        },
                        "default_value": "",
                        "maxlength": "",
                        "placeholder": "",
                        "prepend": "",
                        "append": ""
                    },
                    {
                        "key": "field_640c103352cda",
                        "label": "Answer",
                        "name": "answer",
                        "aria-label": "",
                        "type": "wysiwyg",
                        "instructions": "",
                        "required": 0,
                        "conditional_logic": 0,
                        "wrapper": {
                            "width": "",
                            "class": "",
                            "id": ""
                        },
                        "default_value": "",
                        "tabs": "all",
                        "toolbar": "full",
                        "media_upload": 1,
                        "delay": 0
                    }
                ]
            }
        ],
        "location": [
            [
                {
                    "param": "post_type",
                    "operator": "==",
                    "value": "post"
                }
            ]
        ],
        "menu_order": 0,
        "position": "normal",
        "style": "default",
        "label_placement": "top",
        "instruction_placement": "label",
        "hide_on_screen": "",
        "active": true,
        "description": "",
        "show_in_rest": 0
    }
]